Metadata-Version: 1.0
Name: pyessh
Version: 0.1.3
Summary: A tool for easy to execute commands at multiserver
Home-page: https://github.com/Leviathan1995/pyessh
Author: leviathan1995
Author-email: leviathan0992@gmail.com
License: MIT
Platform: UNKNOWN
